ICEBEAR/__init__.py
ICEBEAR/session_8.py
ICEBEAR/session_9.py
ICEBEAR/tempCodeRunnerFile.py
ICEBEAR-0.2.5.dist-info/METADATA
ICEBEAR-0.2.5.dist-info/WHEEL
ICEBEAR-0.2.5.dist-info/top_level.txt
ICEBEAR-0.2.5.dist-info/RECORD
