Metadata-Version: 2.2
Name: ICEBEAR
Version: 0.2.5
Summary: ENOTION
Author: Chione Raphael
Author-email: toan.nt@enotion.io
License: MIT
Classifier: Programming Language :: Python :: 3
Classifier: License :: OSI Approved :: MIT License
Requires-Dist: numpy
Dynamic: author
Dynamic: author-email
Dynamic: classifier
Dynamic: license
Dynamic: requires-dist
Dynamic: summary
